google/apps/script/type/__init__.py
google/apps/script/type/gapic_metadata.json
google/apps/script/type/gapic_version.py
google/apps/script/type/py.typed
google/apps/script/type/calendar/__init__.py
google/apps/script/type/calendar/gapic_metadata.json
google/apps/script/type/calendar/gapic_version.py
google/apps/script/type/calendar/py.typed
google/apps/script/type/calendar/services/__init__.py
google/apps/script/type/calendar/types/__init__.py
google/apps/script/type/calendar/types/calendar_addon_manifest.py
google/apps/script/type/docs/__init__.py
google/apps/script/type/docs/gapic_metadata.json
google/apps/script/type/docs/gapic_version.py
google/apps/script/type/docs/py.typed
google/apps/script/type/docs/services/__init__.py
google/apps/script/type/docs/types/__init__.py
google/apps/script/type/docs/types/docs_addon_manifest.py
google/apps/script/type/drive/__init__.py
google/apps/script/type/drive/gapic_metadata.json
google/apps/script/type/drive/gapic_version.py
google/apps/script/type/drive/py.typed
google/apps/script/type/drive/services/__init__.py
google/apps/script/type/drive/types/__init__.py
google/apps/script/type/drive/types/drive_addon_manifest.py
google/apps/script/type/gmail/__init__.py
google/apps/script/type/gmail/gapic_metadata.json
google/apps/script/type/gmail/gapic_version.py
google/apps/script/type/gmail/py.typed
google/apps/script/type/gmail/services/__init__.py
google/apps/script/type/gmail/types/__init__.py
google/apps/script/type/gmail/types/gmail_addon_manifest.py
google/apps/script/type/services/__init__.py
google/apps/script/type/sheets/__init__.py
google/apps/script/type/sheets/gapic_metadata.json
google/apps/script/type/sheets/gapic_version.py
google/apps/script/type/sheets/py.typed
google/apps/script/type/sheets/services/__init__.py
google/apps/script/type/sheets/types/__init__.py
google/apps/script/type/sheets/types/sheets_addon_manifest.py
google/apps/script/type/slides/__init__.py
google_apps_script_type-0.5.0.dist-info/licenses/LICENSE
google_apps_script_type-0.5.0.dist-info/METADATA
google_apps_script_type-0.5.0.dist-info/WHEEL
google_apps_script_type-0.5.0.dist-info/top_level.txt
google_apps_script_type-0.5.0.dist-info/RECORD
